README.rst
setup.py
animats.egg-info/PKG-INFO
animats.egg-info/SOURCES.txt
animats.egg-info/dependency_links.txt
animats.egg-info/requires.txt
animats.egg-info/top_level.txt
ecosystem/LICENSE
ecosystem/__init__.py
ecosystem/agents.py
ecosystem/config.py.template
ecosystem/index.html
ecosystem/mdp.py
ecosystem/network.py
ecosystem/network_rl.py
ecosystem/start.sh
ecosystem/utils.py
ecosystem/wsserver.py
ecosystem/images/terrain.png
test/test_agents.py
test/test_mdp.py
test/test_network.py
test/test_network_rl.py